[
    {
        "model": "weeklyhuntapi.improvements",
        "pk": 1,
        "fields": {
            "playbook": 1,
            "description": "Get +1 Sharp, max +3"
        }
    },
    {
        "model": "weeklyhuntapi.improvements",
        "pk": 2,
        "fields": {
            "playbook": 1,
            "description": "Get +1 Charm, max +3"
        }
    },
    {
        "model": "weeklyhuntapi.improvements",
        "pk": 3,
        "fields": {
            "playbook": 1,
            "description": "Get +1 Cool, max +3"
        }
    },
    {
        "model": "weeklyhuntapi.improvements",
        "pk": 4,
        "fields": {
            "playbook": 1,
            "description": "Get +1 Weird, max +3"
        }
    },
    {
        "model": "weeklyhuntapi.improvements",
        "pk": 5,
        "fields": {
            "playbook": 1,
            "description": "Take another Flake move"
        }
    },
    {
        "model": "weeklyhuntapi.improvements",
        "pk": 6,
        "fields": {
            "playbook": 1,
            "description": "Take another Flake move"
        }
    },
    {
        "model": "weeklyhuntapi.improvements",
        "pk": 7,
        "fields": {
            "playbook": 1,
            "description": "Get a haven, like the Expert has, with two options"
        }
    },
    {
        "model": "weeklyhuntapi.improvements",
        "pk": 8,
        "fields": {
            "playbook": 1,
            "description": "Get another option for your haven"
        }
    },
    {
        "model": "weeklyhuntapi.improvements",
        "pk": 9,
        "fields": {
            "playbook": 1,
            "description": "Take a move from another playbook"
        }
    },
    {
        "model": "weeklyhuntapi.improvements",
        "pk": 10,
        "fields": {
            "playbook": 1,
            "description": "Take a move from another playbook"
        }
    },
    {
        "model": "weeklyhuntapi.improvements",
        "pk": 11,
        "fields": {
            "playbook": 2,
            "description": "Get +1 Charm, max +3"
        }
    },
    {
        "model": "weeklyhuntapi.improvements",
        "pk": 12,
        "fields": {
            "playbook": 2,
            "description": "Get +1 Cool, max +2"
        }
    },
    {
        "model": "weeklyhuntapi.improvements",
        "pk": 13,
        "fields": {
            "playbook": 2,
            "description": "Get +1 Sharp, max +2"
        }
    },
    {
        "model": "weeklyhuntapi.improvements",
        "pk": 14,
        "fields": {
            "playbook": 2,
            "description": "Get +1 Tough, max +2"
        }
    },
    {
        "model": "weeklyhuntapi.improvements",
        "pk": 15,
        "fields": {
            "playbook": 2,
            "description": "Take another Mundane move"
        }
    },
    {
        "model": "weeklyhuntapi.improvements",
        "pk": 16,
        "fields": {
            "playbook": 2,
            "description": "Take another Mundane move"
        }
    },
    {
        "model": "weeklyhuntapi.improvements",
        "pk": 17,
        "fields": {
            "playbook": 2,
            "description": "Get back one used Luck point"
        }
    },
    {
        "model": "weeklyhuntapi.improvements",
        "pk": 18,
        "fields": {
            "playbook": 2,
            "description": "Get back one used Luck point"
        }
    },
    {
        "model": "weeklyhuntapi.improvements",
        "pk": 19,
        "fields": {
            "playbook": 2,
            "description": "Take a move from another playbook"
        }
    },
    {
        "model": "weeklyhuntapi.improvements",
        "pk": 20,
        "fields": {
            "playbook": 2,
            "description": "Take a move from another playbook"
        }
    },
    {
        "model": "weeklyhuntapi.improvements",
        "pk": 21,
        "fields": {
            "playbook": 3,
            "description": "Get +1 Charm, max +3"
        }
    },
    {
        "model": "weeklyhuntapi.improvements",
        "pk": 22,
        "fields": {
            "playbook": 3,
            "description": "Get +1 Cool, max +3"
        }
    },
    {
        "model": "weeklyhuntapi.improvements",
        "pk": 23,
        "fields": {
            "playbook": 3,
            "description": "Get +1 Sharp, max +3"
        }
    },
    {
        "model": "weeklyhuntapi.improvements",
        "pk": 24,
        "fields": {
            "playbook": 3,
            "description": "Get +1 Tough, max +3"
        }
    },
    {
        "model": "weeklyhuntapi.improvements",
        "pk": 25,
        "fields": {
            "playbook": 3,
            "description": "Get +1 Weird, max +3"
        }
    },
    {
        "model": "weeklyhuntapi.improvements",
        "pk": 26,
        "fields": {
            "playbook": 3,
            "description": "Take another Chosen move"
        }
    },
    {
        "model": "weeklyhuntapi.improvements",
        "pk": 27,
        "fields": {
            "playbook": 3,
            "description": "Take another Chosen move"
        }
    },
    {
        "model": "weeklyhuntapi.improvements",
        "pk": 28,
        "fields": {
            "playbook": 3,
            "description": "Gain an ally"
        }
    },
    {
        "model": "weeklyhuntapi.improvements",
        "pk": 29,
        "fields": {
            "playbook": 3,
            "description": "Take a move from another playbook"
        }
    },
    {
        "model": "weeklyhuntapi.improvements",
        "pk": 30,
        "fields": {
            "playbook": 3,
            "description": "Take a move from another playbook"
        }
    },
    {
        "model": "weeklyhuntapi.improvements",
        "pk": 31,
        "fields": {
            "playbook": 4,
            "description": "Get +1 Sharp, max +3"
        }
    },
    {
        "model": "weeklyhuntapi.improvements",
        "pk": 32,
        "fields": {
            "playbook": 4,
            "description": "Get +1 Tough, max +2"
        }
    },
    {
        "model": "weeklyhuntapi.improvements",
        "pk": 33,
        "fields": {
            "playbook": 4,
            "description": "Get +1 Cool, max +2"
        }
    },
    {
        "model": "weeklyhuntapi.improvements",
        "pk": 34,
        "fields": {
            "playbook": 4,
            "description": "Get +1 Charm, max +2"
        }
    },
    {
        "model": "weeklyhuntapi.improvements",
        "pk": 35,
        "fields": {
            "playbook": 4,
            "description": "Take another Crooked move"
        }
    },
    {
        "model": "weeklyhuntapi.improvements",
        "pk": 36,
        "fields": {
            "playbook": 4,
            "description": "Take another Crooked move"
        }
    },
    {
        "model": "weeklyhuntapi.improvements",
        "pk": 37,
        "fields": {
            "playbook": 4,
            "description": "Gain an ally: one of your old crew"
        }
    },
    {
        "model": "weeklyhuntapi.improvements",
        "pk": 38,
        "fields": {
            "playbook": 4,
            "description": "Recover a stash of money from the old days, enough to live without care... for a year or two"
        }
    },
    {
        "model": "weeklyhuntapi.improvements",
        "pk": 39,
        "fields": {
            "playbook": 4,
            "description": "Take a move from another playbook"
        }
    },
    {
        "model": "weeklyhuntapi.improvements",
        "pk": 40,
        "fields": {
            "playbook": 4,
            "description": "Take a move from another playbook"
        }
    }
]
